powerline_vcsh/__init__.py
powerline_vcsh/segments.py
powerline_vcsh-1.0.0.dist-info/LICENSE
powerline_vcsh-1.0.0.dist-info/METADATA
powerline_vcsh-1.0.0.dist-info/WHEEL
powerline_vcsh-1.0.0.dist-info/top_level.txt
powerline_vcsh-1.0.0.dist-info/RECORD
